grammar_check-1.3.1.dist-info/DESCRIPTION.rst
grammar_check-1.3.1.dist-info/metadata.json
grammar_check-1.3.1.dist-info/pbr.json
grammar_check-1.3.1.dist-info/METADATA
grammar_check-1.3.1.dist-info/top_level.txt
grammar_check-1.3.1.dist-info/RECORD
grammar_check-1.3.1.dist-info/WHEEL
grammar_check-1.3.1.data/scripts/grammar-check
grammar_check/__init__.py
grammar_check/main.py
grammar_check/__main__.py
grammar_check/which.py
grammar_check/console_mode.py
grammar_check/backports/__init__.py
grammar_check/backports/subprocess.py
grammar_check/LanguageTool-2.2/testrules.bat
grammar_check/LanguageTool-2.2/languagetool-commandline.jar
grammar_check/LanguageTool-2.2/testrules.sh
grammar_check/LanguageTool-2.2/languagetool-standalone.jar
grammar_check/LanguageTool-2.2/COPYING.txt
grammar_check/LanguageTool-2.2/languagetool-server.jar
grammar_check/LanguageTool-2.2/README.txt
grammar_check/LanguageTool-2.2/CHANGES.txt
grammar_check/LanguageTool-2.2/org/languagetool/MessagesBundle_es.properties
grammar_check/LanguageTool-2.2/org/languagetool/MessagesBundle_de.properties
grammar_check/LanguageTool-2.2/org/languagetool/MessagesBundle_ru.properties
grammar_check/LanguageTool-2.2/org/languagetool/MessagesBundle_pt_PT.properties
grammar_check/LanguageTool-2.2/org/languagetool/MessagesBundle_tl.properties
grammar_check/LanguageTool-2.2/org/languagetool/MessagesBundle_pt_BR.properties
grammar_check/LanguageTool-2.2/org/languagetool/MessagesBundle_sk.properties
grammar_check/LanguageTool-2.2/org/languagetool/MessagesBundle_pl.properties
grammar_check/LanguageTool-2.2/org/languagetool/MessagesBundle_nl.properties
grammar_check/LanguageTool-2.2/org/languagetool/MessagesBundle_zh.properties
grammar_check/LanguageTool-2.2/org/languagetool/MessagesBundle_ja.properties
grammar_check/LanguageTool-2.2/org/languagetool/MessagesBundle_be.properties
grammar_check/LanguageTool-2.2/org/languagetool/MessagesBundle_km.properties
grammar_check/LanguageTool-2.2/org/languagetool/MessagesBundle_lt.properties
grammar_check/LanguageTool-2.2/org/languagetool/MessagesBundle_ast.properties
grammar_check/LanguageTool-2.2/org/languagetool/MessagesBundle_eo.properties
grammar_check/LanguageTool-2.2/org/languagetool/MessagesBundle_sl.properties
