Metadata-Version: 2.0
Name: grammar-check
Version: 1.3.1
Summary: Checks grammar using LanguageTool.
Home-page: https://github.com/viraja1/grammar-check
Author: Viraj
Author-email: UNKNOWN
License: UNKNOWN
Platform: UNKNOWN
Classifier: License :: OSI Approved :: GNU Lesser General Public License v3 or later (LGPLv3+)
Classifier: Programming Language :: Python :: 2.7
Classifier: Programming Language :: Python :: 3
Classifier: Programming Language :: Python :: 3.2
Classifier: Programming Language :: Python :: 3.3
